Workbook

Sheet Leia-me
B2: Série Rio — Seis réguas, quatro clubes
B3: Planilha de cálculos auditável · benchmarking de fair play financeiro
B5: COMO USAR ESTA PLANILHA
B6: Esta planilha aplica seis réguas de fair play financeiro (o SSF brasileiro e as cinco ligas que a CBF citou como inspiração) aos quatro grandes do Rio, no exercício 2025. Tudo é calculado por fórmulas: altere um número azul na aba "Dados" e todos os vereditos recalculam.
B8: CONVENÇÃO DE CORES
B9: • Texto AZUL = dado de entrada (input), extraído dos balanços auditados. É o que você pode alterar.
B10: • Texto PRETO = fórmula/cálculo. Não editar — recalcula sozinho.
B11: • Texto VERDE = link puxando de outra aba.
B13: CLASSIFICAÇÃO DE EVIDÊNCIAS
B14: 🟢 documentado — fonte primária nomeada (balanço auditado ou regulamento oficial).
B15: 🟡 inferência forte — dedução de baixo risco a partir de dado documentado.
B16: 🔵 leitura analítica — interpretação própria, não atribuível a uma fonte.
... B35: Exercício analítico independente. Não é relatório oficial de nenhuma entidade. Valores em R$ mil, salvo indicação.

Sheet Dados
A1: DADOS DE ENTRADA — balanços auditados (R$ mil)
A2: Valores em AZUL são inputs (editáveis). Fonte: demonstrações financeiras auditadas 2023–2025.
A4: Métrica (2025, salvo indicado) | B4: Flamengo | C4: Fluminense | D4: Vasco | E4: Botafogo | F4: Fonte / nota
A5: Receita operacional líquida | B5: 1499741 | C5: 758546 | D5: 413878 | E5: 574006 | F5: DRE 2025 (consolidado)
A6: Receita de transferências | B6: 518741 | C6: 233378 | D6: 123866 | E6: 733361 | F6: DRE/NE cessões 2025
A7: Folha ampliada | B7: 711094 | C7: 521663 | D7: 232489 | E7: 438141 | F7: NE pessoal 2025
A8: Amortização de atletas | B8: 243716 | C8: 84353 | D8: 124676 | E8: 236827 | F8: NE intangível 2025
A9: Contribuições patrimoniais (aporte) | B9: 0 | C9: 0 | D9: 0 | E9: 0 | F9: Mutações PL 2025
A10: Resultado operacional (antes financeiro) | B10: 350886 | C10: 100370 | D10: -126472 | E10: -274066 | F10: DRE 2025 (fiel; embute não-recorrentes)
A11: EBITDA Recorrente Puro (hors mutation) | B11: 135411 | C11: -255894 | D11: -150304 | E11: -26481 | F11: cálculo recorrente 2025
A12: Dívida onerosa (empréstimos CP+LP) | B12: 0 | C12: 37775 | D12: 99379 | E12: 138972 | F12: NE empréstimos 2025
A13: Parcelamento fiscal (CP+LP) | B13: 162316 | C13: 469980 | D13: 251905 | E13: 318507 | F13: NE obrigações tributárias 2025
A14: Ativo circulante | B14: 558966 | C14: 181086 | D14: 180041 | E14: 401563 | F14: BP 2025
A15: Passivo circulante | B15: 592332 | C15: 483813 | D15: 384505 | E15: 1353595 | F15: BP 2025
A16: Patrimônio líquido | B16: 954125 | C16: -182045 | D16: -647490 | E16: -431917 | F16: BP 2025
... A19: Aporte trienal 2023-25 (PSR) | B19: 0 | C19: 0 | D19: 120000 | E19: 268394 | F19: mutações PL 2023+24+25

Sheet 1-SSF Brasil
A1: Brasil — SSF / ANRESF (cobrança 2026)
A2: Três requisitos: Equilíbrio (déficit ≤ max(30.000; 2,5% receita)), Custo com Elenco (custo÷receita relevante ≤90% em 2026) e Endividamento (OLCP÷receita ≤70% em 2026). Receita relevante = receita líquida + transferências + aportes.
A3: Fonte: Regulamento SSF/CBF 2025 (Arts. 49–50; Seções 4 e 5).
A5: Clube | B5: Receita relev. | C5: Custo elenco | D5: Índice custo | E5: Result. op. | F5: Lim. déficit | G5: Endivid. (OLCP) | H5: Índice end. | I5: Veredito
A6: Flamengo | B6: =Dados!B5+Dados!B6+Dados!B9 -> 2018482 | C6: =Dados!B7+Dados!B8 -> 954810 | D6: =C6/B6 -> 0.4730337 | E6: =Dados!B10 -> 350886 | F6: =-MAX(30000,0.025*Dados!B5) -> -37493.525 | G6: =Dados!B12+Dados!B13 -> 162316 | H6: =G6/Dados!B5 -> 0.10822935 | I6: =IF(AND(D6<=0.9,E6>=F6,H6<=0.7),"APROVADO","REPROVADO") -> APROVADO
A7: Fluminense | B7: =Dados!C5+Dados!C6+Dados!C9 -> 991924 | C7: =Dados!C7+Dados!C8 -> 606016 | D7: =C7/B7 -> 0.61095003 | E7: =Dados!C10 -> 100370 | F7: =-MAX(30000,0.025*Dados!C5) -> -30000 | G7: =Dados!C12+Dados!C13 -> 507755 | H7: =G7/Dados!C5 -> 0.66937931 | I7: =IF(AND(D7<=0.9,E7>=F7,H7<=0.7),"APROVADO","REPROVADO") -> APROVADO
A8: Vasco | B8: =Dados!D5+Dados!D6+Dados!D9 -> 537744 | C8: =Dados!D7+Dados!D8 -> 357165 | D8: =C8/B8 -> 0.66419151 | E8: =Dados!D10 -> -126472 | F8: =-MAX(30000,0.025*Dados!D5) -> -30000 | G8: =Dados!D12+Dados!D13 -> 351284 | H8: =G8/Dados!D5 -> 0.8487622 | I8: =IF(AND(D8<=0.9,E8>=F8,H8<=0.7),"APROVADO","REPROVADO") -> REPROVADO
A9: Botafogo | B9: =Dados!E5+Dados!E6+Dados!E9 -> 1307367 | C9: =Dados!E7+Dados!E8 -> 674968 | D9: =C9/B9 -> 0.51628043 | E9: =Dados!E10 -> -274066 | F9: =-MAX(30000,0.025*Dados!E5) -> -30000 | G9: =Dados!E12+Dados!E13 -> 457479 | H9: =G9/Dados!E5 -> 0.79699341 | I9: =IF(AND(D9<=0.9,E9>=F9,H9<=0.7),"APROVADO","REPROVADO") -> REPROVADO

Sheet 2-Inglaterra PSR
A1: Inglaterra — Premier League (PSR)
A2: Perda acumulada trienal (2023–2025). Teto bruto £105M≈R$700.000; trava de perda própria £15M≈R$100.000 (perda além disso precisa estar coberta por aporte). Conversão só para escala.
A3: Fonte: Premier League Handbook, Section E (premierleague.com).
A5: Clube | B5: Perda acum. 3 anos | C5: Aporte 3 anos | D5: Teto bruto (R$700k) | E5: Veredito bruto | F5: Trava própria (R$100k) | G5: Veredito próprio
A6: Flamengo | B6: =Dados!B18 -> 699959 | C6: =Dados!B19 -> 0 | D6: -700000 | E6: =IF(B6>=D6,"APROVADO","REPROVADO") -> APROVADO | F6: -100000 | G6: =IF(OR(B6>=-100000,B6+C6>=-100000),"APROVADO","REPROVADO") -> APROVADO
A7: Fluminense | B7: =Dados!C18 -> 75831 | C7: =Dados!C19 -> 0 | D7: -700000 | E7: =IF(B7>=D7,"APROVADO","REPROVADO") -> APROVADO | F7: -100000 | G7: =IF(OR(B7>=-100000,B7+C7>=-100000),"APROVADO","REPROVADO") -> APROVADO
A8: Vasco | B8: =Dados!D18 -> -389555 | C8: =Dados!D19 -> 120000 | D8: -700000 | E8: =IF(B8>=D8,"APROVADO","REPROVADO") -> APROVADO | F8: -100000 | G8: =IF(OR(B8>=-100000,B8+C8>=-100000),"APROVADO","REPROVADO") -> REPROVADO
A9: Botafogo | B9: =Dados!E18 -> -613752 | C9: =Dados!E19 -> 268394 | D9: -700000 | E9: =IF(B9>=D9,"APROVADO","REPROVADO") -> APROVADO | F9: -100000 | G9: =IF(OR(B9>=-100000,B9+C9>=-100000),"APROVADO","REPROVADO") -> REPROVADO

Sheet 3-Espanha LCPD
A1: Espanha — La Liga (LCPD)
A2: Teto = Receita operacional líquida − Dívida (empréstimos + parcelamento fiscal), confrontado ao gasto com elenco (folha + amortização). Versão simplificada (despesa não-esportiva não segregável; vendas de atletas não entram no teto — limitação documentada).
A3: Fonte: LaLiga, Normas de Elaboración de Presupuestos, Art. 38 (laliga.com/transparency).
A5: Clube | B5: Receita op. líq. | C5: Dívida total | D5: Teto (R−D) | E5: Gasto elenco | F5: Margem | G5: Veredito
A6: Flamengo | B6: =Dados!B5 -> 1499741 | C6: =Dados!B12+Dados!B13 -> 162316 | D6: =B6-C6 -> 1337425 | E6: ='1-SSF Brasil'!C6 -> 954810 | F6: =D6-E6 -> 382615 | G6: =IF(F6>=0,"APROVADO","REPROVADO") -> APROVADO
A7: Fluminense | B7: =Dados!C5 -> 758546 | C7: =Dados!C12+Dados!C13 -> 507755 | D7: =B7-C7 -> 250791 | E7: ='1-SSF Brasil'!C7 -> 606016 | F7: =D7-E7 -> -355225 | G7: =IF(F7>=0,"APROVADO","REPROVADO") -> REPROVADO
A8: Vasco | B8: =Dados!D5 -> 413878 | C8: =Dados!D12+Dados!D13 -> 351284 | D8: =B8-C8 -> 62594 | E8: ='1-SSF Brasil'!C8 -> 357165 | F8: =D8-E8 -> -294571 | G8: =IF(F8>=0,"APROVADO","REPROVADO") -> REPROVADO
A9: Botafogo | B9: =Dados!E5 -> 574006 | C9: =Dados!E12+Dados!E13 -> 457479 | D9: =B9-C9 -> 116527 | E9: ='1-SSF Brasil'!C9 -> 674968 | F9: =D9-E9 -> -558441 | G9: =IF(F9>=0,"APROVADO","REPROVADO") -> REPROVADO

Sheet 4-Itália FIGC
A1: Itália — FIGC (três indicadores)
A2: Liquidità (AC/PC ≥0,80), Indebitamento (dívida/valor da produção ≤1,20), CLA/R (custo elenco/receita ≤0,70). Valor da produção = receita líquida + transferências. Reprova se falhar qualquer um.
A3: Fonte: FIGC, NOIF Titolo VI art. 85 (figc.it).
A5: Clube | B5: Liquidità | C5: ≥0,80? | D5: Indebit. | E5: ≤1,20? | F5: CLA/R | G5: ≤0,70? | H5: Veredito
A6: Flamengo | B6: =Dados!B14/Dados!B15 -> 0.9436701 | C6: =IF(B6>=0.8,"✓","✗") -> ✓ | D6: =(Dados!B12+Dados!B13)/(Dados!B5+Dados!B6) -> 0.080414886 | E6: =IF(D6<=1.2,"✓","✗") -> ✓ | F6: =(Dados!B7+Dados!B8)/(Dados!B5+Dados!B6) -> 0.4730337 | G6: =IF(F6<=0.7,"✓","✗") -> ✓ | H6: =IF(AND(B6>=0.8,D6<=1.2,F6<=0.7),"APROVADO","REPROVADO") -> APROVADO
A7: Fluminense | B7: =Dados!C14/Dados!C15 -> 0.37428924 | C7: =IF(B7>=0.8,"✓","✗") -> ✗ | D7: =(Dados!C12+Dados!C13)/(Dados!C5+Dados!C6) -> 0.51188902 | E7: =IF(D7<=1.2,"✓","✗") -> ✓ | F7: =(Dados!C7+Dados!C8)/(Dados!C5+Dados!C6) -> 0.61095003 | G7: =IF(F7<=0.7,"✓","✗") -> ✓ | H7: =IF(AND(B7>=0.8,D7<=1.2,F7<=0.7),"APROVADO","REPROVADO") -> REPROVADO
A8: Vasco | B8: =Dados!D14/Dados!D15 -> 0.46824099 | C8: =IF(B8>=0.8,"✓","✗") -> ✗ | D8: =(Dados!D12+Dados!D13)/(Dados!D5+Dados!D6) -> 0.65325508 | E8: =IF(D8<=1.2,"✓","✗") -> ✓ | F8: =(Dados!D7+Dados!D8)/(Dados!D5+Dados!D6) -> 0.66419151 | G8: =IF(F8<=0.7,"✓","✗") -> ✓ | H8: =IF(AND(B8>=0.8,D8<=1.2,F8<=0.7),"APROVADO","REPROVADO") -> REPROVADO
A9: Botafogo | B9: =Dados!E14/Dados!E15 -> 0.29666407 | C9: =IF(B9>=0.8,"✓","✗") -> ✗ | D9: =(Dados!E12+Dados!E13)/(Dados!E5+Dados!E6) -> 0.34992393 | E9: =IF(D9<=1.2,"✓","✗") -> ✓ | F9: =(Dados!E7+Dados!E8)/(Dados!E5+Dados!E6) -> 0.51628043 | G9: =IF(F9<=0.7,"✓","✗") -> ✓ | H9: =IF(AND(B9>=0.8,D9<=1.2,F9<=0.7),"APROVADO","REPROVADO") -> REPROVADO

Sheet 5-Alemanha DFL
A1: Alemanha — DFL (licenciamento)
A2: Licenciamento por patrimônio (proxy do critério de capital): patrimônio líquido negativo = falha. Caixa como referência de liquidez. Régua mais conceitual — DFL real usa projeção de caixa, ausente dos balanços (limitação).
A3: Fonte: DFL, Licensing Regulations (Lizenzierungsordnung) (dfl.de).
A5: Clube | B5: Patrimônio líquido | C5: Caixa | D5: Veredito (equity)
A6: Flamengo | B6: =Dados!B16 -> 954125 | C6: =Dados!B17 -> 242854 | D6: =IF(B6>=0,"APROVADO","REPROVADO") -> APROVADO
A7: Fluminense | B7: =Dados!C16 -> -182045 | C7: =Dados!C17 -> 34526 | D7: =IF(B7>=0,"APROVADO","REPROVADO") -> REPROVADO
A8: Vasco | B8: =Dados!D16 -> -647490 | C8: =Dados!D17 -> 60344 | D8: =IF(B8>=0,"APROVADO","REPROVADO") -> REPROVADO
A9: Botafogo | B9: =Dados!E16 -> -431917 | C9: =Dados!E17 -> 80000 | D9: =IF(B9>=0,"APROVADO","REPROVADO") -> REPROVADO

Sheet 6-França DNCG
A1: França — DNCG
A2: Resultado da operação corrente (hors mutation = EBITDA Recorrente Puro, exclui transferências). Aporte do controlador isolado. Veredito: hors mutation ≥ 0 = aprovado.
A3: Fonte: Code du sport / Règlement DNCG (lfp.fr).
A5: Clube | B5: Hors mutation | C5: Transferências | D5: Aporte | E5: Veredito
A6: Flamengo | B6: =Dados!B11 -> 135411 | C6: =Dados!B6 -> 518741 | D6: =Dados!B9 -> 0 | E6: =IF(B6>=0,"APROVADO","REPROVADO") -> APROVADO
A7: Fluminense | B7: =Dados!C11 -> -255894 | C7: =Dados!C6 -> 233378 | D7: =Dados!C9 -> 0 | E7: =IF(B7>=0,"APROVADO","REPROVADO") -> REPROVADO
A8: Vasco | B8: =Dados!D11 -> -150304 | C8: =Dados!D6 -> 123866 | D8: =Dados!D9 -> 0 | E8: =IF(B8>=0,"APROVADO","REPROVADO") -> REPROVADO
A9: Botafogo | B9: =Dados!E11 -> -26481 | C9: =Dados!E6 -> 733361 | D9: =Dados!E9 -> 0 | E9: =IF(B9>=0,"APROVADO","REPROVADO") -> REPROVADO

Sheet Síntese
A1: Síntese — o mesmo clube sob as seis réguas
A2: Veredito de cada clube sob cada régua (2025; SSF cobrança 2026; PSR perda própria). Puxa o veredito de cada aba — recalcula se você alterar os dados.
A3: Leitura: Flamengo passa em todas; Vasco e Botafogo reprovam em todas; Fluminense é a divergência.
A5: Clube | B5: Brasil | C5: Inglaterra | D5: Espanha | E5: Itália | F5: Alemanha | G5: França
A6: Flamengo | B6: ='1-SSF Brasil'!I6 -> APROVADO | C6: ='2-Inglaterra PSR'!G6 -> APROVADO | D6: ='3-Espanha LCPD'!G6 -> APROVADO | E6: ='4-Itália FIGC'!H6 -> APROVADO | F6: ='5-Alemanha DFL'!D6 -> APROVADO | G6: ='6-França DNCG'!E6 -> APROVADO
A7: Fluminense | B7: ='1-SSF Brasil'!I7 -> APROVADO | C7: ='2-Inglaterra PSR'!G7 -> APROVADO | D7: ='3-Espanha LCPD'!G7 -> REPROVADO | E7: ='4-Itália FIGC'!H7 -> REPROVADO | F7: ='5-Alemanha DFL'!D7 -> REPROVADO | G7: ='6-França DNCG'!E7 -> REPROVADO
A8: Vasco | B8: ='1-SSF Brasil'!I8 -> REPROVADO | C8: ='2-Inglaterra PSR'!G8 -> REPROVADO | D8: ='3-Espanha LCPD'!G8 -> REPROVADO | E8: ='4-Itália FIGC'!H8 -> REPROVADO | F8: ='5-Alemanha DFL'!D8 -> REPROVADO | G8: ='6-França DNCG'!E8 -> REPROVADO
A9: Botafogo | B9: ='1-SSF Brasil'!I9 -> REPROVADO | C9: ='2-Inglaterra PSR'!G9 -> REPROVADO | D9: ='3-Espanha LCPD'!G9 -> REPROVADO | E9: ='4-Itália FIGC'!H9 -> REPROVADO | F9: ='5-Alemanha DFL'!D9 -> REPROVADO | G9: ='6-França DNCG'!E9 -> REPROVADO
